jgp_report_creditos/__init__.py
jgp_report_creditos/report.py
jgp_report_creditos/test.py
jgp_report_creditos/core/__init__.py
jgp_report_creditos/core/deposito.py
jgp_report_creditos/core/rutas.py
jgp_report_creditos/core/contrato/__init__.py
jgp_report_creditos/core/contrato/v1/__init__.py
jgp_report_creditos/core/contrato/v1/base.py
jgp_report_creditos/core/contrato/v1/contratos.py
jgp_report_creditos/core/exception/__init__.py
jgp_report_creditos/core/exception/exception.py
jgp_report_creditos/resources/img/logo_jgp.png
jgp_report_creditos/template/__init__.py
jgp_report_creditos/template/components.py
jgp_report_creditos/template/template.py
jgp_report_creditos/tests/__init__.py
jgp_report_creditos/tests/test_contratos.py
jgp_report_creditos/tests/test_deposito.py
jgp_report_creditos-0.0.22.dist-info/LICENSE
jgp_report_creditos-0.0.22.dist-info/METADATA
jgp_report_creditos-0.0.22.dist-info/WHEEL
jgp_report_creditos-0.0.22.dist-info/top_level.txt
jgp_report_creditos-0.0.22.dist-info/RECORD
