Metadata-Version: 2.1
Name: jgp-report-creditos
Version: 0.0.22
Summary: Librería con funciones y herramientas útiles exclusivas para jgp
Home-page: https://gitlab.com/develop-team-jdgp/jgp-report-creditos.git
Author: JGP Dev
Author-email: jgpdev20@gmail.com
License: MIT
Keywords: python,primer paquete jgp
Platform: UNKNOWN
License-File: LICENSE
